kilter/protocol/__init__.py
kilter/protocol/buffer.py
kilter/protocol/core.py
kilter/protocol/exceptions.py
kilter/protocol/messages.py
kilter/protocol/py.typed
kilter_protocol-0.6.0.dist-info/WHEEL
kilter_protocol-0.6.0.dist-info/METADATA
kilter_protocol-0.6.0.dist-info/RECORD
