Metadata-Version: 2.1
Name: kilter.protocol
Version: 0.6.0
Summary: Parsers and state machines for the Sendmail milter communications protocol
Author-email: Dom Sekotill <dom.sekotill@kodo.org.uk>
Requires-Python: ~=3.10
Classifier: Development Status :: 1 - Planning
Classifier: Intended Audience :: Telecommunications Industry
Classifier: License :: OSI Approved :: Mozilla Public License 2.0 (MPL 2.0)
Classifier: Topic :: Communications :: Email :: Filters
Requires-Dist: typing-extensions
Requires-Dist: coverage[toml] ; extra == "coverage"
Requires-Dist: kodo.plugins.cover-test-context ; extra == "coverage"
Requires-Dist: sphinx ~=5.0 ; extra == "docs"
Requires-Dist: myst-parser ; extra == "docs"
Requires-Dist: sphinx-rtd-theme ; extra == "docs"
Project-URL: Documentation, https://kilter.kodo.org.uk/kilter.protocol/
Project-URL: Issues, https://github.com/domsekotill/kilter.protocol/issues
Project-URL: Source, https://github.com/domsekotill/kilter.protocol
Provides-Extra: coverage
Provides-Extra: docs
